shournal_to_snakemake/__init__.py
shournal_to_snakemake/__main__.py
shournal_to_snakemake/abstract_class_helpers.py
shournal_to_snakemake/app.py
shournal_to_snakemake/argparse_helpers.py
shournal_to_snakemake/command.py
shournal_to_snakemake/command_loader.py
shournal_to_snakemake/rule_printer.py
shournal_to_snakemake/shell_tokenizer.py
shournal_to_snakemake/snakemake_rule.py
shournal_to_snakemake/util.py
shournal_to_snakemake-0.1.dist-info/LICENSE.md
shournal_to_snakemake-0.1.dist-info/METADATA
shournal_to_snakemake-0.1.dist-info/WHEEL
shournal_to_snakemake-0.1.dist-info/entry_points.txt
shournal_to_snakemake-0.1.dist-info/top_level.txt
shournal_to_snakemake-0.1.dist-info/RECORD
