Metadata-Version: 2.1
Name: shournal-to-snakemake
Version: 0.1
Summary: Transform a command series from shournal into Snakemake rules
Home-page: https://github.com/snakemake/shournal-to-snakemake
Author: Tycho Kirchner
Author-email: tychokirchner@mail.de
License: MIT
Platform: UNKNOWN
Classifier: Environment :: Console
Classifier: Programming Language :: Python
Classifier: Programming Language :: Python :: 3
Classifier: License :: OSI Approved :: MIT License
Classifier: Operating System :: OS Independent
Requires-Dist: ordered-set
